CPU/CPU.v
module fwd(input [7:0] data1, data2, output reg [7:0] out);
    always @(*)
        #1 out = data2;
endmodule

module add(input [7:0] data1, data2, output reg [7:0] out);
    always @(*)
        #2 out = data1 + data2;
endmodule

module ann(input [7:0] data1, data2, output reg [7:0] out);
    always @(*)
        #1 out = data1 & data2;
endmodule

module orr(input [7:0] data1, data2, output reg [7:0] out);
    always @(*)
       #1  out = data1 | data2;
endmodule

module alu(
    input [7:0] data1, data2,
    input [2:0] operation,
    output reg [7:0] result 
);
    wire [7:0] out1, out2, out3, out4;

    fwd fwd_dut(.data1(data1), .data2(data2), .out(out1));
    add add_dut(.data1(data1), .data2(data2), .out(out2));
    ann and_dut(.data1(data1), .data2(data2), .out(out3));
    orr orr_dut(.data1(data1), .data2(data2), .out(out4));

    always @(*) begin
        case (operation)
            3'b000: result = out1; 
            3'b001: result = out2;
            3'b010: result = out3;
            3'b011: result = out4;
        endcase
    end
endmodule

module reg_file(
    input [7:0] IN, 
    output reg [7:0] OUT1,OUT2,
    input [2:0] INADDRESS,OUT1ADDRESS,OUT2ADDRESS, 
    input WRITE, CLK, RESET
);
    reg [0:7][7:0] registerfile;
    integer i;
    always @(posedge CLK)begin

        if (RESET==1'b1) begin
            // all set to zero
            for(i = 0; i < 8; i = i + 1) begin
                registerfile[i] = 'b0;
            end
            //registerfile = '0;
        end
        else if(WRITE == 1'b1) begin
            #1
            registerfile[INADDRESS] = IN;
        end
    end
    always @(*) begin
        #2 
        OUT1 = registerfile[OUT1ADDRESS];
        OUT2 = registerfile[OUT2ADDRESS];
    end
endmodule

module controlUnit(
    input [31:0] instruction, 
    output reg MUX1, MUX2, 
    output reg [2:0] ALUOP
);
    always @(*) begin
        ALUOP = instruction[26:24];
        if(ALUOP == 3'b000) MUX1 = 1;
        else MUX1 = 0;
        if(ALUOP == 3'b100) MUX2 = 1;
        else MUX2 = 0;
        if(ALUOP == 3'b101) ALUOP = 3'b000;
    end
endmodule

module program_counter(input RESET, input CLK, output reg [31:0] OUT);
    always@(posedge CLK, RESET) begin
        if(RESET) OUT <= 'b0;
        else #1 OUT <= OUT + 4;
    end
endmodule

module cpu (
    output [31:0] PC,
    input [31:0] INSTRUCTION, 
    input CLK, RESET
);
    wire [7:0] OUT1,OUT2;
    reg  [7:0] IN;
    reg  [2:0] INADDRESS,OUT1ADDRESS,OUT2ADDRESS; 
    reg WRITE = 1;

    program_counter pc_dut(.RESET(RESET), .CLK(CLK), .OUT(PC));

    reg_file registerFile (.IN(IN), 
                           .OUT1(OUT1), 
                           .OUT2(OUT2), 
                           .INADDRESS(INADDRESS), 
                           .OUT1ADDRESS(OUT1ADDRESS),
                           .OUT2ADDRESS(OUT2ADDRESS), 
                           .WRITE(WRITE), 
                           .CLK(CLK),
                           .RESET(RESET)
                           );

    wire mux1, mux2;
    wire [2:0] ALUOPOUT;

    controlUnit controler(.instruction(INSTRUCTION), .MUX1(mux1), .MUX2(mux2), .ALUOP(ALUOPOUT));

    wire [7:0] OUT;
    reg  [7:0] IN1,IN2;
    reg  [2:0] ALUOPIN;

    alu ALU(.data1(IN1), .operation(ALUOPIN), .result(OUT), .data2(IN2));

    reg[7:0] mux2out;

    always @(*) begin
        // Decoding
        #1
        INADDRESS   = INSTRUCTION[18:16];
        OUT1ADDRESS = INSTRUCTION[10: 8];
        OUT2ADDRESS = INSTRUCTION[ 2: 0];
        
        IN1 = OUT1;
        IN  = OUT; 

        // MUX for selecting subtracting or addition
        if(mux2) begin
            ALUOPIN = 3'b001;
            #1 mux2out = ~OUT2 + 'b1;
        end else begin
            ALUOPIN = ALUOPOUT;
            mux2out = OUT2;
        end
        
        // MUX for selecting immediate or register file output 2
        if(mux1) begin 
            IN2 = INSTRUCTION[7:0];
        end else begin
            IN2 = mux2out;
        end
    end
endmodule

// Computer Architecture (CO224) - Lab 05
// Design: Testbench of Integrated CPU of Simple Processor
// Author: Isuru Nawinne

module cpu_tb;

    reg CLK, RESET;
    wire [31:0] PC;
    reg [31:0] INSTRUCTION;
    reg [7:0] instr_mem [1023:0];
    /* 
    ------------------------
     SIMPLE INSTRUCTION MEM
    ------------------------
    */
    
    // TODO: Initialize an array of registers (8x1024) named 'instr_mem' to be used as instruction memory
    
    // TODO: Create combinational logic to support CPU instruction fetching, given the Program Counter(PC) value 
    //       (make sure you include the delay for instruction fetching here)
    integer i;
    initial
    begin
        // Initialize instruction memory with the set of instructions you need execute on CPU
        // METHOD 1: manually loading instructions to instr_mem
        //{instr_mem[10'd3], instr_mem[10'd2], instr_mem[10'd1], instr_mem[10'd0]} = 32'b00000000000001000000000000000101;
        //{instr_mem[10'd7], instr_mem[10'd6], instr_mem[10'd5], instr_mem[10'd4]} = 32'b00000000000000100000000000001001;
        //{instr_mem[10'd11], instr_mem[10'd10], instr_mem[10'd9], instr_mem[10'd8]} = 32'b00000010000001100000010000000010;
        
        // METHOD 2: loading instr_mem content from instr_mem.mem file
        $readmemb("instr_mem.mem", instr_mem);
    end
    
    /* 
    -----
     CPU
    -----
    */
    cpu mycpu(PC, INSTRUCTION, CLK, RESET);

    initial
    begin
        // generate files needed to plot the waveform using GTKWave
        $dumpfile("dump.vcd");
		$dumpvars(0, cpu_tb);
        CLK = 1'b0;
        // TODO: Reset the CPU (by giving a pulse to RESET signal) to start the program execution      
        RESET = 1'b1;
        #5
        RESET= 0;
        for(i =0; i<7; i=i+1) begin
            #1 INSTRUCTION = {instr_mem[3+PC], instr_mem[2+PC], instr_mem[1+PC], instr_mem[PC]};
            // $dumpvars(1,cpu_dut.registerfile[i]);
            @(posedge CLK);
        end
        // finish simulation after some time
        #500
        $finish;
    end
    
    // clock signal generation
    always
        #4 CLK = ~CLK;
        

endmodule

// module tb;

//     wire [31:0] PC;
//     reg [31:0] INSTRUCTION;
//     reg CLK = 0, RESET = 1;

//     reg [7:0] instr_mem [1023:0];

//     cpu cpu_dut (.PC(PC), .INSTRUCTION(INSTRUCTION), .CLK(CLK), .RESET(RESET));

//     initial forever begin
//         #4 CLK = ~CLK;
//     end

//     integer i;
//     initial begin
//         $monitor();
//         $readmemb("instr_mem.mem", instr_mem);
//         $dumpfile("dump.vcd");
//         // for(i=0; i<8; i++) begin
//         //     $dumpvars(0,cpu_dut.registerFile.reg_file.registerfile[i]);
//         //     // $dumpvars(1,cpu_dut.registerFile.reg_file[1]);
//         // end
//         $dumpvars(0, cpu_dut);

//         #5 RESET = 0;
//         #2 INSTRUCTION = {instr_mem[3+PC], instr_mem[2+PC], instr_mem[1+PC], instr_mem[PC]};
//         #500
//         $finish();
//     end

// endmodule


        
        // @(posedge CLK);
        // #1 RESET = 0;
        // @(posedge CLK);
        // #1 INSTRUCTION = 'b00000000_00000000_00000000_00001011; // loadi r0, #11 
        // #2
        // @(posedge CLK);
        // #1 INSTRUCTION = 'b00000000_00000001_00000000_00000011; // loadi r1, #3
        // #2
        // @(posedge CLK);
        // #1 INSTRUCTION = 'b00000100_00000010_00000000_00000001; // sub r2, r0, r1 
        // #2
        // @(posedge CLK);
        // #1 INSTRUCTION = 'b00000001_00000011_00000000_00000001; // add r3, r0, r1 
        // #2
        // @(posedge CLK);
        // #1 INSTRUCTION = 'b00000010_00000100_00000000_00000001; // and r4, r0, r1 
        // #2
        // @(posedge CLK);
        // #1 INSTRUCTION = 'b00000011_00000101_00000000_00000001; // or r5, r0, r1 
        // #2
        // @(posedge CLK);
        // #1 INSTRUCTION = 'b00000101_00000110_00000000_00000001; // mov r6, r1 
        // #20


        // ins_reg[0] = 32'b00000000_00000000_00000000_00001011;//loadi r0, #11
        // ins_reg[1] = 32'b00000000_00000001_00000000_00000011;// loadi r1, #3
        // ins_reg[2] = 32'b00000100_00000010_00000000_00000001;// sub r2, r0, r1
        // ins_reg[3] = 32'b00000001_00000011_00000000_00000001;// add r3, r0, r1
        // ins_reg[4] = 32'b00000010_00000100_00000000_00000001;// and r4, r0, r1 
        // ins_reg[5] = 32'b00000011_00000101_00000000_00000001;// or r5, r0, r1 
        // ins_reg[6] = 32'b00000101_00000110_00000000_00000001;// mov r6, r1

CPU/dump.vcd
$date
	Fri May 26 01:10:45 2023
$end
$version
	Icarus Verilog
$end
$timescale
	1s
$end
$scope module cpu_tb $end
$var wire 32 ! PC [31:0] $end
$var reg 1 " CLK $end
$var reg 32 # INSTRUCTION [31:0] $end
$var reg 1 $ RESET $end
$var integer 32 % i [31:0] $end
$scope module mycpu $end
$var wire 1 " CLK $end
$var wire 32 & INSTRUCTION [31:0] $end
$var wire 1 $ RESET $end
$var wire 1 ' mux2 $end
$var wire 1 ( mux1 $end
$var wire 32 ) PC [31:0] $end
$var wire 8 * OUT2 [7:0] $end
$var wire 8 + OUT1 [7:0] $end
$var wire 8 , OUT [7:0] $end
$var wire 3 - ALUOPOUT [2:0] $end
$var reg 3 . ALUOPIN [2:0] $end
$var reg 8 / IN [7:0] $end
$var reg 8 0 IN1 [7:0] $end
$var reg 8 1 IN2 [7:0] $end
$var reg 3 2 INADDRESS [2:0] $end
$var reg 3 3 OUT1ADDRESS [2:0] $end
$var reg 3 4 OUT2ADDRESS [2:0] $end
$var reg 1 5 WRITE $end
$var reg 8 6 mux2out [7:0] $end
$scope module ALU $end
$var wire 8 7 data1 [7:0] $end
$var wire 8 8 data2 [7:0] $end
$var wire 3 9 operation [2:0] $end
$var wire 8 : out4 [7:0] $end
$var wire 8 ; out3 [7:0] $end
$var wire 8 < out2 [7:0] $end
$var wire 8 = out1 [7:0] $end
$var reg 8 > result [7:0] $end
$scope module add_dut $end
$var wire 8 ? data1 [7:0] $end
$var wire 8 @ data2 [7:0] $end
$var reg 8 A out [7:0] $end
$upscope $end
$scope module and_dut $end
$var wire 8 B data1 [7:0] $end
$var wire 8 C data2 [7:0] $end
$var reg 8 D out [7:0] $end
$upscope $end
$scope module fwd_dut $end
$var wire 8 E data1 [7:0] $end
$var wire 8 F data2 [7:0] $end
$var reg 8 G out [7:0] $end
$upscope $end
$scope module orr_dut $end
$var wire 8 H data1 [7:0] $end
$var wire 8 I data2 [7:0] $end
$var reg 8 J out [7:0] $end
$upscope $end
$upscope $end
$scope module controler $end
$var wire 32 K instruction [31:0] $end
$var reg 3 L ALUOP [2:0] $end
$var reg 1 ( MUX1 $end
$var reg 1 ' MUX2 $end
$upscope $end
$scope module pc_dut $end
$var wire 1 " CLK $end
$var wire 1 $ RESET $end
$var reg 32 M OUT [31:0] $end
$upscope $end
$scope module registerFile $end
$var wire 1 " CLK $end
$var wire 8 N IN [7:0] $end
$var wire 3 O INADDRESS [2:0] $end
$var wire 3 P OUT1ADDRESS [2:0] $end
$var wire 3 Q OUT2ADDRESS [2:0] $end
$var wire 1 $ RESET $end
$var wire 1 5 WRITE $end
$var reg 8 R OUT1 [7:0] $end
$var reg 8 S OUT2 [7:0] $end
$var reg 64 T registerfile [63:0] $end
$var integer 32 U i [31:0] $end
$upscope $end
$upscope $end
$upscope $end
$enddefinitions $end
#0
$dumpvars
bx U
bx T
bx S
bx R
bx Q
bx P
bx O
bx N
b0 M
bx L
bx K
bx J
bx I
bx H
bx G
bx F
bx E
bx D
bx C
bx B
bx A
bx @
bx ?
bx >
bx =
bx <
bx ;
bx :
bx 9
bx 8
bx 7
bx 6
15
bx 4
bx 3
bx 2
bx 1
bx 0
bx /
bx .
bx -
bx ,
bx +
bx *
b0 )
x(
x'
bx &
bx %
1$
bx #
0"
b0 !
$end
#4
b0 T
b1000 U
1"
#5
b0 %
0$
#6
b100 !
b100 )
b100 M
0'
1(
b0 -
b0 L
b1011 #
b1011 &
b1011 K
#7
b1011 1
b1011 8
b1011 @
b1011 C
b1011 F
b1011 I
b0 .
b0 9
b11 4
b11 Q
b0 3
b0 P
b0 2
b0 O
#8
b1011 ,
b1011 >
bx1x11 :
bx1x11 J
b0x0xx ;
b0x0xx D
b1011 =
b1011 G
0"
#9
b0 6
b1011 /
b1011 N
b0 0
b0 7
b0 ?
b0 B
b0 E
b0 H
b0 *
b0 S
b0 +
b0 R
#10
b0 ;
b0 D
b1011 :
b1011 J
#11
b1011 <
b1011 A
#12
b1 %
1"
#13
b1000 !
b1000 )
b1000 M
b101100000000000000000000000000000000000000000000000000000000 T
b10000000000000011 #
b10000000000000011 &
b10000000000000011 K
#14
b11 1
b11 8
b11 @
b11 C
b11 F
b11 I
b1 2
b1 O
#15
b11 ,
b11 >
b11 :
b11 J
b11 =
b11 G
b1011 +
b1011 R
#16
b11 /
b11 N
b1011 0
b1011 7
b1011 ?
b1011 B
b1011 E
b1011 H
b11 <
b11 A
0"
#17
b11 ;
b11 D
b1011 :
b1011 J
#18
b1110 <
b1110 A
#20
b10 %
1"
#21
b1100 !
b1100 )
b1100 M
1'
0(
b100 -
b100 L
b100000000100000000000000001 #
b100000000100000000000000001 &
b100000000100000000000000001 K
b101100000011000000000000000000000000000000000000000000000000 T
#22
b1110 ,
b1110 >
b1 .
b1 9
b1 4
b1 Q
b10 2
b10 O
#23
b11111101 1
b11111101 8
b11111101 @
b11111101 C
b11111101 F
b11111101 I
b11111101 6
b11 *
b11 S
#24
b11111111 :
b11111111 J
b1001 ;
b1001 D
b11111101 =
b11111101 G
0"
#25
b1000 ,
b1000 >
b1000 <
b1000 A
#26
b1000 /
b1000 N
#28
b11 %
1"
#29
b10000 !
b10000 )
b10000 M
0'
b1 -
b1 L
b101100000011000010000000000000000000000000000000000000000000 T
b1000000110000000000000001 #
b1000000110000000000000001 &
b1000000110000000000000001 K
#30
b11 1
b11 8
b11 @
b11 C
b11 F
b11 I
b11 6
b11 2
b11 O
#31
b11 ;
b11 D
b1011 :
b1011 J
b11 =
b11 G
#32
b1110 ,
b1110 >
b1110 <
b1110 A
0"
#33
b1110 /
b1110 N
#36
b100 %
1"
#37
b10100 !
b10100 )
b10100 M
b10 -
b10 L
b10000001000000000000000001 #
b10000001000000000000000001 &
b10000001000000000000000001 K
b101100000011000010000000111000000000000000000000000000000000 T
#38
b11 ,
b11 >
b10 .
b10 9
b100 2
b100 O
#39
b11 /
b11 N
#40
0"
#44
b101 %
1"
#45
b11000 !
b11000 )
b11000 M
b11 -
b11 L
b101100000011000010000000111000000011000000000000000000000000 T
b11000001010000000000000001 #
b11000001010000000000000001 &
b11000001010000000000000001 K
#46
b1011 ,
b1011 >
b11 .
b11 9
b101 2
b101 O
#47
b1011 /
b1011 N
#48
0"
#52
b110 %
1"
#53
b11100 !
b11100 )
b11100 M
b0 -
b0 L
b101000001100000000000000001 #
b101000001100000000000000001 &
b101000001100000000000000001 K
b101100000011000010000000111000000011000010110000000000000000 T
#54
b11 ,
b11 >
b0 .
b0 9
b110 2
b110 O
#55
b11 /
b11 N
#56
0"
#60
b111 %
1"
#61
b100000 !
b100000 )
b100000 M
b101100000011000010000000111000000011000010110000001100000000 T
#64
0"
#68
1"
#69
b100100 !
b100100 )
b100100 M
#72
0"
#76
1"
#77
b101000 !
b101000 )
b101000 M
#80
0"
#84
1"
#85
b101100 !
b101100 )
b101100 M
#88
0"
#92
1"
#93
b110000 !
b110000 )
b110000 M
#96
0"
#100
1"
#101
b110100 !
b110100 )
b110100 M
#104
0"
#108
1"
#109
b111000 !
b111000 )
b111000 M
#112
0"
#116
1"
#117
b111100 !
b111100 )
b111100 M
#120
0"
#124
1"
#125
b1000000 !
b1000000 )
b1000000 M
#128
0"
#132
1"
#133
b1000100 !
b1000100 )
b1000100 M
#136
0"
#140
1"
#141
b1001000 !
b1001000 )
b1001000 M
#144
0"
#148
1"
#149
b1001100 !
b1001100 )
b1001100 M
#152
0"
#156
1"
#157
b1010000 !
b1010000 )
b1010000 M
#160
0"
#164
1"
#165
b1010100 !
b1010100 )
b1010100 M
#168
0"
#172
1"
#173
b1011000 !
b1011000 )
b1011000 M
#176
0"
#180
1"
#181
b1011100 !
b1011100 )
b1011100 M
#184
0"
#188
1"
#189
b1100000 !
b1100000 )
b1100000 M
#192
0"
#196
1"
#197
b1100100 !
b1100100 )
b1100100 M
#200
0"
#204
1"
#205
b1101000 !
b1101000 )
b1101000 M
#208
0"
#212
1"
#213
b1101100 !
b1101100 )
b1101100 M
#216
0"
#220
1"
#221
b1110000 !
b1110000 )
b1110000 M
#224
0"
#228
1"
#229
b1110100 !
b1110100 )
b1110100 M
#232
0"
#236
1"
#237
b1111000 !
b1111000 )
b1111000 M
#240
0"
#244
1"
#245
b1111100 !
b1111100 )
b1111100 M
#248
0"
#252
1"
#253
b10000000 !
b10000000 )
b10000000 M
#256
0"
#260
1"
#261
b10000100 !
b10000100 )
b10000100 M
#264
0"
#268
1"
#269
b10001000 !
b10001000 )
b10001000 M
#272
0"
#276
1"
#277
b10001100 !
b10001100 )
b10001100 M
#280
0"
#284
1"
#285
b10010000 !
b10010000 )
b10010000 M
#288
0"
#292
1"
#293
b10010100 !
b10010100 )
b10010100 M
#296
0"
#300
1"
#301
b10011000 !
b10011000 )
b10011000 M
#304
0"
#308
1"
#309
b10011100 !
b10011100 )
b10011100 M
#312
0"
#316
1"
#317
b10100000 !
b10100000 )
b10100000 M
#320
0"
#324
1"
#325
b10100100 !
b10100100 )
b10100100 M
#328
0"
#332
1"
#333
b10101000 !
b10101000 )
b10101000 M
#336
0"
#340
1"
#341
b10101100 !
b10101100 )
b10101100 M
#344
0"
#348
1"
#349
b10110000 !
b10110000 )
b10110000 M
#352
0"
#356
1"
#357
b10110100 !
b10110100 )
b10110100 M
#360
0"
#364
1"
#365
b10111000 !
b10111000 )
b10111000 M
#368
0"
#372
1"
#373
b10111100 !
b10111100 )
b10111100 M
#376
0"
#380
1"
#381
b11000000 !
b11000000 )
b11000000 M
#384
0"
#388
1"
#389
b11000100 !
b11000100 )
b11000100 M
#392
0"
#396
1"
#397
b11001000 !
b11001000 )
b11001000 M
#400
0"
#404
1"
#405
b11001100 !
b11001100 )
b11001100 M
#408
0"
#412
1"
#413
b11010000 !
b11010000 )
b11010000 M
#416
0"
#420
1"
#421
b11010100 !
b11010100 )
b11010100 M
#424
0"
#428
1"
#429
b11011000 !
b11011000 )
b11011000 M
#432
0"
#436
1"
#437
b11011100 !
b11011100 )
b11011100 M
#440
0"
#444
1"
#445
b11100000 !
b11100000 )
b11100000 M
#448
0"
#452
1"
#453
b11100100 !
b11100100 )
b11100100 M
#456
0"
#460
1"
#461
b11101000 !
b11101000 )
b11101000 M
#464
0"
#468
1"
#469
b11101100 !
b11101100 )
b11101100 M
#472
0"
#476
1"
#477
b11110000 !
b11110000 )
b11110000 M
#480
0"
#484
1"
#485
b11110100 !
b11110100 )
b11110100 M
#488
0"
#492
1"
#493
b11111000 !
b11111000 )
b11111000 M
#496
0"
#500
1"
#501
b11111100 !
b11111100 )
b11111100 M
#504
0"
#508
1"
#509
b100000000 !
b100000000 )
b100000000 M
#512
0"
#516
1"
#517
b100000100 !
b100000100 )
b100000100 M
#520
0"
#524
1"
#525
b100001000 !
b100001000 )
b100001000 M
#528
0"
#532
1"
#533
b100001100 !
b100001100 )
b100001100 M
#536
0"
#540
1"
#541
b100010000 !
b100010000 )
b100010000 M
#544
0"
#548
1"
#549
b100010100 !
b100010100 )
b100010100 M
#552
0"
#556
1"
#557
b100011000 !
b100011000 )
b100011000 M
