Register File/RegisterFile.v
module reg_file(input [7:0] IN, 
                output reg [7:0] OUT1,OUT2,
                input [2:0] INADDRESS,OUT1ADDRESS,OUT2ADDRESS, 
                input WRITE, CLK, RESET
                );

    reg [0:7][7:0] registerfile;
    integer i;
    always @(*)begin

        if (RESET=='b1) begin
            // all set to zero
            for(i = 0; i < 8; i = i + 1) begin
                registerfile[i] = 'b0;
            end
            //registerfile = '0;
        end
        case (INADDRESS) 
            3'b000 : registerfile[0] = IN;
            3'b001 : registerfile[1] = IN;
            3'b010 : registerfile[2] = IN;
            3'b011 : registerfile[3] = IN;
            3'b100 : registerfile[4] = IN;
            3'b101 : registerfile[5] = IN;
            3'b110 : registerfile[6] = IN;
            3'b111 : registerfile[7] = IN;
        endcase

        case (OUT1ADDRESS) 
            3'b000 : OUT1 = registerfile[0];
            3'b001 : OUT1 = registerfile[1];
            3'b010 : OUT1 = registerfile[2];
            3'b011 : OUT1 = registerfile[3];
            3'b100 : OUT1 = registerfile[4];
            3'b101 : OUT1 = registerfile[5];
            3'b110 : OUT1 = registerfile[6];
            3'b111 : OUT1 = registerfile[7];
        endcase

        case (OUT2ADDRESS) 
            3'b000 : OUT2 = registerfile[0];
            3'b001 : OUT2 = registerfile[1];
            3'b010 : OUT2 = registerfile[2];
            3'b011 : OUT2 = registerfile[3];
            3'b100 : OUT2 = registerfile[4];
            3'b101 : OUT2 = registerfile[5];
            3'b110 : OUT2 = registerfile[6];
            3'b111 : OUT2 = registerfile[7];
        endcase
        
    end
endmodule

module tb;
    reg [7:0] IN;
    wire [7:0] OUT1,OUT2;
    reg [2:0] INADDRESS,OUT1ADDRESS,OUT2ADDRESS; 
    reg WRITE = 0, RESET = 0;
    reg CLK = 0;

    initial forever begin
        #5 CLK = ~CLK;
    end

    reg_file dut(IN, OUT1, OUT2, INADDRESS, OUT1ADDRESS, OUT2ADDRESS, WRITE, CLK, RESET);

    integer i;
    initial begin
        $dumpfile("RegisterFile.vcd");
        $dumpvars(0, dut);
        RESET = 1; WRITE = 1; #5 RESET=0;

        for (i = 0; i < 8; i = i + 1) begin
            #1 @(posedge CLK); IN = i; INADDRESS = i;
        end

        
        for(i = 0; i < 8; i=i+1) begin
            #1 @(posedge CLK); OUT1ADDRESS = i;
            #1 @(posedge CLK); OUT2ADDRESS = 7-i;
        end

        #20
        $finish();
        
    end
endmodule

Register File/dump.vcd
$date
	Wed May 10 10:45:47 2023
$end
$version
	Icarus Verilog
$end
$timescale
	1s
$end
$scope module tb $end
$scope module dut $end
$var wire 1 ! CLK $end
$var wire 8 " IN [7:0] $end
$var wire 3 # INADDRESS [2:0] $end
$var wire 3 $ OUT1ADDRESS [2:0] $end
$var wire 3 % OUT2ADDRESS [2:0] $end
$var wire 1 & RESET $end
$var wire 1 ' WRITE $end
$var reg 8 ( OUT1 [7:0] $end
$var reg 8 ) OUT2 [7:0] $end
$var reg 64 * registerfile [63:0] $end
$var integer 32 + i [31:0] $end
$upscope $end
$upscope $end
$enddefinitions $end
#0
$dumpvars
b1000 +
b0 *
bx )
bx (
1'
1&
bx %
bx $
bx #
bx "
0!
$end
#5
0&
1!
#10
0!
#15
b0 #
b0 "
1!
#20
0!
#25
b1000000000000000000000000000000000000000000000000 *
b1 #
b1 "
1!
#30
0!
#35
b1000000100000000000000000000000000000000000000000 *
b10 #
b10 "
1!
#40
0!
#45
b1000000100000001100000000000000000000000000000000 *
b11 #
b11 "
1!
#50
0!
#55
b1000000100000001100000100000000000000000000000000 *
b100 #
b100 "
1!
#60
0!
#65
b1000000100000001100000100000001010000000000000000 *
b101 #
b101 "
1!
#70
0!
#75
b1000000100000001100000100000001010000011000000000 *
b110 #
b110 "
1!
#80
0!
#85
b1000000100000001100000100000001010000011000000111 *
b111 #
b111 "
1!
#90
0!
#95
b0 (
b0 $
1!
#100
0!
#105
b111 )
b111 %
1!
#110
0!
#115
b1 (
b1 $
1!
#120
0!
#125
b110 )
b110 %
1!
#130
0!
#135
b10 (
b10 $
1!
#140
0!
#145
b101 )
b101 %
1!
#150
0!
#155
b11 (
b11 $
1!
#160
0!
#165
b100 )
b100 %
1!
#170
0!
#175
b100 (
b100 $
1!
#180
0!
#185
b11 )
b11 %
1!
#190
0!
#195
b101 (
b101 $
1!
#200
0!
#205
b10 )
b10 %
1!
#210
0!
#215
b110 (
b110 $
1!
#220
0!
#225
b1 )
b1 %
1!
#230
0!
#235
b111 (
b111 $
1!
#240
0!
#245
b0 )
b0 %
1!
